iriiifassemble/__init__.py
iriiifassemble/config/config.yml
iriiifassemble/finder/__init__.py
iriiifassemble/finder/finder.py
iriiifassemble/generate.py
iriiifassemble-0.1.3.dist-info/METADATA
iriiifassemble-0.1.3.dist-info/WHEEL
iriiifassemble-0.1.3.dist-info/entry_points.txt
iriiifassemble-0.1.3.dist-info/RECORD
