Metadata-Version: 2.1
Name: iriiifassemble
Version: 0.1.3
Summary: 
Author: Mark Baggett
Author-email: markpbaggett@gmail.com
Requires-Python: >=3.12,<4.0
Classifier: Programming Language :: Python :: 3
Classifier: Programming Language :: Python :: 3.12
Requires-Dist: click (>=8.1.7,<9.0.0)
Requires-Dist: httpx (>=0.27.2,<0.28.0)
Requires-Dist: pyyaml (>=6.0.2,<7.0.0)
Requires-Dist: tqdm (>=4.66.6,<5.0.0)
